rormula-0.1.11.dist-info/METADATA
rormula-0.1.11.dist-info/WHEEL
rormula/__init__.py
rormula/rormula.cpython-312-aarch64-linux-gnu.so
rormula/rormula.pyi
rormula-0.1.11.dist-info/RECORD
