Metadata-Version: 2.4
Name: rormula
Version: 0.1.11
Classifier: Programming Language :: Rust
Classifier: Programming Language :: Python :: Implementation :: CPython
Requires-Dist: pandas
Summary: Formula parser and evaluator for Wilkinson notation
Keywords: design of experiments,Wilkinson,parser,eval,doe
Author-email: Behrang Shafei <behrang.shafei@basf.com>
License: BSD-3-Clause
Requires-Python: >=3.10
Project-URL: repository, https://github.com/basf/rormula
Project-URL: homepage, https://github.com/basf/rormula
